Metadata-Version: 2.4
Name: llama-index-callbacks-aim
Version: 0.4.1
Summary: llama-index callbacks aim integration
Author-email: Your Name <you@example.com>
License-Expression: MIT
License-File: LICENSE
Requires-Python: >=3.9
Requires-Dist: aim<4,>=3.17.5
Requires-Dist: jwt<2,>=1.3.1
Requires-Dist: llama-index-core<0.13,>=0.10.1
